prettymetrics/__init__.py
prettymetrics/clf.py
prettymetrics/cli.py
prettymetrics/reg.py
prettymetrics-0.0.3.dist-info/AUTHORS.rst
prettymetrics-0.0.3.dist-info/LICENSE
prettymetrics-0.0.3.dist-info/METADATA
prettymetrics-0.0.3.dist-info/WHEEL
prettymetrics-0.0.3.dist-info/entry_points.txt
prettymetrics-0.0.3.dist-info/top_level.txt
prettymetrics-0.0.3.dist-info/RECORD
