Metadata-Version: 2.1
Name: prettymetrics
Version: 0.0.3
Summary: One place metrics for various ML regression and classification algorithms 
Home-page: https://github.com/tactlabs/prettymetrics
Author: Raja CSP Raman
Author-email: info@tactii.com
License: MIT
Keywords: prettymetrics
Platform: UNKNOWN
Classifier: Development Status :: 2 - Pre-Alpha
Classifier: Intended Audience :: Developers
Classifier: License :: OSI Approved :: MIT License
Classifier: Natural Language :: English
Classifier: Programming Language :: Python :: 3.6
Requires-Python: >=3.6
Requires-Dist: click (==7.1.2)
Requires-Dist: joblib (==1.0.0)
Requires-Dist: lightgbm (==2.3.1)
Requires-Dist: numpy (==1.19.1)
Requires-Dist: pandas (==1.0.5)
Requires-Dist: pytest (==5.4.3)
Requires-Dist: PyYAML (==5.3.1)
Requires-Dist: scikit-learn (==0.24.2)
Requires-Dist: scipy (==1.5.4)
Requires-Dist: six (==1.15.0)
Requires-Dist: tqdm (==4.56.0)
Requires-Dist: xgboost (==1.1.1)
